VIZ/sensor1.v
module sensor;

 integer i;
 reg [31:0] heat;
 reg clk;

 initial begin
	 clk = 0;
	 forever #5 clk = !clk;
 end

 initial begin
	 $dumpfile("simple.vcd");
	 $dumpvars(0,sensor);
	 heat = 0;
	 for(i=0;i<=100;i++) begin
		 @(posedge clk);
		 heat = heat + 5;
	 end
	 $finish;
 end
endmodule

VIZ/simple.vcd
$date
	Thu Jun  9 23:20:06 2022
$end
$version
	Icarus Verilog
$end
$timescale
	1s
$end
$scope module sensor $end
$var reg 1 ! clk $end
$var reg 32 " heat [31:0] $end
$var integer 32 # i [31:0] $end
$upscope $end
$enddefinitions $end
#0
$dumpvars
b0 #
b0 "
0!
$end
#5
b1 #
b101 "
1!
#10
0!
#15
b10 #
b1010 "
1!
#20
0!
#25
b11 #
b1111 "
1!
#30
0!
#35
b100 #
b10100 "
1!
#40
0!
#45
b101 #
b11001 "
1!
#50
0!
#55
b110 #
b11110 "
1!
#60
0!
#65
b111 #
b100011 "
1!
#70
0!
#75
b1000 #
b101000 "
1!
#80
0!
#85
b1001 #
b101101 "
1!
#90
0!
#95
b1010 #
b110010 "
1!
#100
0!
#105
b1011 #
b110111 "
1!
#110
0!
#115
b1100 #
b111100 "
1!
#120
0!
#125
b1101 #
b1000001 "
1!
#130
0!
#135
b1110 #
b1000110 "
1!
#140
0!
#145
b1111 #
b1001011 "
1!
#150
0!
#155
b10000 #
b1010000 "
1!
#160
0!
#165
b10001 #
b1010101 "
1!
#170
0!
#175
b10010 #
b1011010 "
1!
#180
0!
#185
b10011 #
b1011111 "
1!
#190
0!
#195
b10100 #
b1100100 "
1!
#200
0!
#205
b10101 #
b1101001 "
1!
#210
0!
#215
b10110 #
b1101110 "
1!
#220
0!
#225
b10111 #
b1110011 "
1!
#230
0!
#235
b11000 #
b1111000 "
1!
#240
0!
#245
b11001 #
b1111101 "
1!
#250
0!
#255
b11010 #
b10000010 "
1!
#260
0!
#265
b11011 #
b10000111 "
1!
#270
0!
#275
b11100 #
b10001100 "
1!
#280
0!
#285
b11101 #
b10010001 "
1!
#290
0!
#295
b11110 #
b10010110 "
1!
#300
0!
#305
b11111 #
b10011011 "
1!
#310
0!
#315
b100000 #
b10100000 "
1!
#320
0!
#325
b100001 #
b10100101 "
1!
#330
0!
#335
b100010 #
b10101010 "
1!
#340
0!
#345
b100011 #
b10101111 "
1!
#350
0!
#355
b100100 #
b10110100 "
1!
#360
0!
#365
b100101 #
b10111001 "
1!
#370
0!
#375
b100110 #
b10111110 "
1!
#380
0!
#385
b100111 #
b11000011 "
1!
#390
0!
#395
b101000 #
b11001000 "
1!
#400
0!
#405
b101001 #
b11001101 "
1!
#410
0!
#415
b101010 #
b11010010 "
1!
#420
0!
#425
b101011 #
b11010111 "
1!
#430
0!
#435
b101100 #
b11011100 "
1!
#440
0!
#445
b101101 #
b11100001 "
1!
#450
0!
#455
b101110 #
b11100110 "
1!
#460
0!
#465
b101111 #
b11101011 "
1!
#470
0!
#475
b110000 #
b11110000 "
1!
#480
0!
#485
b110001 #
b11110101 "
1!
#490
0!
#495
b110010 #
b11111010 "
1!
#500
0!
#505
b110011 #
b11111111 "
1!
#510
0!
#515
b110100 #
b100000100 "
1!
#520
0!
#525
b110101 #
b100001001 "
1!
#530
0!
#535
b110110 #
b100001110 "
1!
#540
0!
#545
b110111 #
b100010011 "
1!
#550
0!
#555
b111000 #
b100011000 "
1!
#560
0!
#565
b111001 #
b100011101 "
1!
#570
0!
#575
b111010 #
b100100010 "
1!
#580
0!
#585
b111011 #
b100100111 "
1!
#590
0!
#595
b111100 #
b100101100 "
1!
#600
0!
#605
b111101 #
b100110001 "
1!
#610
0!
#615
b111110 #
b100110110 "
1!
#620
0!
#625
b111111 #
b100111011 "
1!
#630
0!
#635
b1000000 #
b101000000 "
1!
#640
0!
#645
b1000001 #
b101000101 "
1!
#650
0!
#655
b1000010 #
b101001010 "
1!
#660
0!
#665
b1000011 #
b101001111 "
1!
#670
0!
#675
b1000100 #
b101010100 "
1!
#680
0!
#685
b1000101 #
b101011001 "
1!
#690
0!
#695
b1000110 #
b101011110 "
1!
#700
0!
#705
b1000111 #
b101100011 "
1!
#710
0!
#715
b1001000 #
b101101000 "
1!
#720
0!
#725
b1001001 #
b101101101 "
1!
#730
0!
#735
b1001010 #
b101110010 "
1!
#740
0!
#745
b1001011 #
b101110111 "
1!
#750
0!
#755
b1001100 #
b101111100 "
1!
#760
0!
#765
b1001101 #
b110000001 "
1!
#770
0!
#775
b1001110 #
b110000110 "
1!
#780
0!
#785
b1001111 #
b110001011 "
1!
#790
0!
#795
b1010000 #
b110010000 "
1!
#800
0!
#805
b1010001 #
b110010101 "
1!
#810
0!
#815
b1010010 #
b110011010 "
1!
#820
0!
#825
b1010011 #
b110011111 "
1!
#830
0!
#835
b1010100 #
b110100100 "
1!
#840
0!
#845
b1010101 #
b110101001 "
1!
#850
0!
#855
b1010110 #
b110101110 "
1!
#860
0!
#865
b1010111 #
b110110011 "
1!
#870
0!
#875
b1011000 #
b110111000 "
1!
#880
0!
#885
b1011001 #
b110111101 "
1!
#890
0!
#895
b1011010 #
b111000010 "
1!
#900
0!
#905
b1011011 #
b111000111 "
1!
#910
0!
#915
b1011100 #
b111001100 "
1!
#920
0!
#925
b1011101 #
b111010001 "
1!
#930
0!
#935
b1011110 #
b111010110 "
1!
#940
0!
#945
b1011111 #
b111011011 "
1!
#950
0!
#955
b1100000 #
b111100000 "
1!
#960
0!
#965
b1100001 #
b111100101 "
1!
#970
0!
#975
b1100010 #
b111101010 "
1!
#980
0!
#985
b1100011 #
b111101111 "
1!
#990
0!
#995
b1100100 #
b111110100 "
1!
#1000
0!
#1005
b1100101 #
b111111001 "
1!
